TL_kinetics/__init__.py
TL_kinetics/kinetics.py
tl_kinetics-0.0.2.dist-info/licenses/LICENSE
tl_kinetics-0.0.2.dist-info/METADATA
tl_kinetics-0.0.2.dist-info/WHEEL
tl_kinetics-0.0.2.dist-info/top_level.txt
tl_kinetics-0.0.2.dist-info/RECORD
