Metadata-Version: 2.4
Name: TL_kinetics
Version: 0.0.2
Summary: Python tools for simulation of Thermoluminescence (TL) glow curves
Author: Jorge Eduardo Tenopala Peralta
License: MIT
Requires-Python: >=3.8
License-File: LICENSE
Requires-Dist: numpy
Requires-Dist: matplotlib
Requires-Dist: pandas
Requires-Dist: scikit-learn
Requires-Dist: ipython
Dynamic: license-file
